README.rst
setup.py
PyCovenantSQL.egg-info/PKG-INFO
PyCovenantSQL.egg-info/SOURCES.txt
PyCovenantSQL.egg-info/dependency_links.txt
PyCovenantSQL.egg-info/requires.txt
PyCovenantSQL.egg-info/top_level.txt
pycovenantsql/__init__.py
pycovenantsql/_compat.py
pycovenantsql/connections.py
pycovenantsql/converters.py
pycovenantsql/cursors.py
pycovenantsql/e2ee.py
pycovenantsql/err.py
pycovenantsql/optionfile.py
pycovenantsql/times.py
pycovenantsql/constants/FIELD_TYPE.py
pycovenantsql/constants/__init__.py
pycovenantsql/ext/__init__.py
pycovenantsql/ext/peewee.py