Metadata-Version: 1.1
Name: PyCovenantSQL
Version: 0.1.5
Summary: Pure Python CovenantSQL Driver
Home-page: https://github.com/CovenantSQL/cql-python-driver/
Author: laodouya
Author-email: jin.xu@CovenantSQL.io
License: Apache 2.0 Licence
Project-URL: Documentation, https://pycovenantsql.readthedocs.io/
Keywords: CovenantSQL,driver,database
Platform: UNKNOWN
Classifier: Development Status :: 2 - Pre-Alpha
Classifier: Programming Language :: Python :: 2
Classifier: Programming Language :: Python :: 2.7
Classifier: Programming Language :: Python :: 3
Classifier: Programming Language :: Python :: 3.6
Classifier: Programming Language :: Python :: 3.7
Classifier: Programming Language :: Python :: Implementation :: CPython
Classifier: Programming Language :: Python :: Implementation :: PyPy
Classifier: License :: OSI Approved :: Apache Software License
Classifier: Intended Audience :: Developers
Classifier: Topic :: Database
